anydo_api-0.0.1.dist-info/WHEEL
anydo_api-0.0.1.dist-info/top_level.txt
anydo_api-0.0.1.dist-info/metadata.json
anydo_api-0.0.1.dist-info/DESCRIPTION.rst
anydo_api-0.0.1.dist-info/RECORD
anydo_api-0.0.1.dist-info/METADATA
anydo_api/resource.py
anydo_api/__init__.py
anydo_api/user.py
anydo_api/constants.py
anydo_api/category.py
anydo_api/errors.py
anydo_api/task.py
anydo_api/request.py
anydo_api/client.py
