Metadata-Version: 2.0
Name: anydo-api
Version: 0.0.1
Summary: Unofficial AnyDo API client in object-oriented style.
Home-page: https://github.com/aliaksandrb/anydo_api
Author: Aliaksandr Buhayeu
Author-email: aliaksandr.buhayeu@gmail.com
License: MIT
Keywords: anydo,anydo_api,anydo_client
Platform: UNKNOWN
Classifier: Development Status :: 3 - Alpha
Classifier: Intended Audience :: Developers
Classifier: License :: OSI Approved :: MIT License
Classifier: Natural Language :: English
Classifier: Programming Language :: Python :: 2
Classifier: Programming Language :: Python :: 2.7
Classifier: Programming Language :: Python :: 3
Classifier: Programming Language :: Python :: 3.4
Classifier: Topic :: Software Development :: Libraries
Classifier: Topic :: Utilities
Requires-Dist: requests (>=2.8.0)
Provides-Extra: :python_version in "2.7"
Requires-Dist: contextlib2; extra == ':python_version in "2.7"'
Requires-Dist: mock; extra == ':python_version in "2.7"'
